gtci/__init__.py
gtci/main.py
gtci/utils.py
gtci-1.1.2.dist-info/LICENSE
gtci-1.1.2.dist-info/METADATA
gtci-1.1.2.dist-info/WHEEL
gtci-1.1.2.dist-info/entry_points.txt
gtci-1.1.2.dist-info/top_level.txt
gtci-1.1.2.dist-info/RECORD
